aolab_aopy-0.9.3.dist-info/licenses/LICENSE
aopy/__init__.py
aopy/torch.py
aopy/tutorial_functions.py
aopy/analysis/__init__.py
aopy/analysis/accllr.py
aopy/analysis/base.py
aopy/analysis/behavior.py
aopy/analysis/celltype.py
aopy/analysis/connectivity.py
aopy/analysis/controllers.py
aopy/analysis/kfdecoder.py
aopy/analysis/latency.py
aopy/analysis/tuning.py
aopy/config/210910_ecog_signal_path.xlsx
aopy/config/221021_opto_signal_path.xlsx
aopy/config/244ch_viventi_ecog_elec_to_pos.xlsx
aopy/config/251202_64ch_emg_signal_path.xlsx
aopy/config/32ch_fiber_optic_assy_elec_to_pos.xlsx
aopy/config/64ch_emg_gr08mm1305_elec_to_pos.xlsx
aopy/config/affi_lm1_ecog244_sulci.png
aopy/config/beignet_lm1_ecog244_sulci.png
aopy/config/lasers.yaml
aopy/config/qwalor_447nm_ch2.yaml
aopy/config/task_codes.yaml
aopy/config/neuropixel_insert_ch_mapping/NP_Insert137_ch_mapping.xlsx
aopy/config/neuropixel_insert_ch_mapping/NP_Insert137_signal_path.xlsx
aopy/config/neuropixel_insert_ch_mapping/NP_Insert72_ch_mapping.xlsx
aopy/config/neuropixel_insert_ch_mapping/NP_Insert72_signal_path.xlsx
aopy/config/neuropixel_insert_ch_mapping/NP_Insert_angle_alignment.xlsx
aopy/data/__init__.py
aopy/data/base.py
aopy/data/bmi3d.py
aopy/data/db.py
aopy/data/eye.py
aopy/data/neuropixel.py
aopy/data/optitrack.py
aopy/data/peslab.py
aopy/postproc/__init__.py
aopy/postproc/base.py
aopy/postproc/bmi3d.py
aopy/postproc/eye.py
aopy/postproc/neuropixel.py
aopy/precondition/__init__.py
aopy/precondition/base.py
aopy/precondition/eye.py
aopy/preproc/__init__.py
aopy/preproc/base.py
aopy/preproc/bmi3d.py
aopy/preproc/laser.py
aopy/preproc/neuropixel.py
aopy/preproc/oculomatic.py
aopy/preproc/optitrack.py
aopy/preproc/quality.py
aopy/preproc/wrappers.py
aopy/utils/__init__.py
aopy/utils/base.py
aopy/utils/memory.py
aopy/visualization/__init__.py
aopy/visualization/animation.py
aopy/visualization/base.py
aopy/visualization/bmi3d.py
aopy/visualization/eye.py
aopy/whitematter/__init__.py
aopy/whitematter/arraymethods.py
aopy/whitematter/dataset.py
aolab_aopy-0.9.3.dist-info/METADATA
aolab_aopy-0.9.3.dist-info/WHEEL
aolab_aopy-0.9.3.dist-info/top_level.txt
aolab_aopy-0.9.3.dist-info/RECORD
